model_porter/__init__.py
model_porter/admin_urls.py
model_porter/apps.py
model_porter/config.py
model_porter/files.py
model_porter/forms.py
model_porter/model_porter.py
model_porter/repository.py
model_porter/serialisation.py
model_porter/storage.py
model_porter/support_mixin.py
model_porter/utilities.py
model_porter/wagtail_hooks.py
model_porter/management/__init__.py
model_porter/management/commands/__init__.py
model_porter/management/commands/pack_repository.py
model_porter/templates/model_porter/choose_import_file.html
model_porter/templates/model_porter/confirm_import.html
model_porter/templates/model_porter/dashboard.html
model_porter/templates/model_porter/import_summary.html
model_porter/views/__init__.py
model_porter/views/actions.py
model_porter/views/dashboard.py
model_porter-4.1.1.dist-info/AUTHORS.txt
model_porter-4.1.1.dist-info/LICENSE.txt
model_porter-4.1.1.dist-info/METADATA
model_porter-4.1.1.dist-info/WHEEL
model_porter-4.1.1.dist-info/top_level.txt
model_porter-4.1.1.dist-info/zip-safe
model_porter-4.1.1.dist-info/RECORD
